adapol/__init__.py
adapol/aaa.py
adapol/anacont.py
adapol/fit_utils.py
adapol/hybfit.py
adapol-0.1.0.dist-info/METADATA
adapol-0.1.0.dist-info/WHEEL
adapol-0.1.0.dist-info/top_level.txt
adapol-0.1.0.dist-info/RECORD
