Metadata-Version: 2.1
Name: adapol
Version: 0.1.0
Summary: Adaptive Pole Fitting for Quantum Many-Body Physics 
Author-email: Zhen Huang <hertz@berkeley.edu>, Chia-Nan Yeh <cyeh@flatironinstitute.org>, Nils Wentzell <nwentzell@flatironinstitute.org>, Jason Kaye <jkaye@flatironinstitute.org>, Lin Lin <linlin@berkeley.edu>
Project-URL: Homepage, https://flatironinstitute.github.io/adapol
Project-URL: Bug Tracker, https://github.com/flatironinstitute/adapol/issues
Keywords: Bath,Fitting,Hybridization,DMFT,Matsubara
Classifier: Programming Language :: Python :: 3
Classifier: License :: OSI Approved :: GNU General Public License v3 (GPLv3)
Classifier: Operating System :: OS Independent
Requires-Python: >=3.7
Requires-Dist: numpy
Requires-Dist: scipy
Requires-Dist: cvxpy
